<?xml version="1.0"?>
<!DOCTYPE hibernate-mapping PUBLIC "-//Hibernate/Hibernate Mapping DTD 3.0//EN"
"http://hibernate.sourceforge.net/hibernate-mapping-3.0.dtd">
<!-- Generated 9 juin 2010 15:04:15 by Hibernate Tools 3.2.4.GA -->
<hibernate-mapping>
    <class name="com.bitc.cms.hdata.ContentGuidedTourClt" table="content_guided_tour_clt">
        <id name="cltId" type="java.lang.Integer">
            <column name="clt_id" />
            <generator class="identity" />
        </id>
        <many-to-one name="contentGuidedTour" class="com.bitc.cms.hdata.ContentGuidedTour" fetch="select">
            <column name="content_id" not-null="true" />
        </many-to-one>
        <property name="title" type="string">
            <column name="title" length="300" />
        </property>
        <property name="abstract_" type="string">
            <column name="abstract" length="2000" />
        </property>
        <property name="body" type="string">
            <column name="body" length="16777215" />
        </property>
        <property name="info" type="string">
            <column name="info" length="16777215" />
        </property>
        <property name="smallImage" type="string">
            <column name="small_image" length="300" />
        </property>
        <property name="bigImage" type="string">
            <column name="big_image" length="300" />
        </property>
        <property name="url" type="string">
            <column name="url" length="300" />
        </property>
        <property name="urlLabel" type="string">
            <column name="url_label" length="200" />
        </property>
        <property name="culture" type="string">
            <column name="culture" length="7" />
        </property>
        <property name="openCount" type="java.lang.Integer">
            <column name="open_count" />
        </property>
        <property name="commentCount" type="java.lang.Integer">
            <column name="comment_count" />
        </property>
        <property name="sourceTitle" type="string">
            <column name="source_title" length="300" />
        </property>
        <property name="sourceAbstract" type="string">
            <column name="source_abstract" length="2000" />
        </property>
        <property name="sourceBody" type="string">
            <column name="source_body" length="16777215" />
        </property>
        <property name="sourceInfo" type="string">
            <column name="source_info" length="1000"/>
        </property>
        <property name="sourceId" type="java.lang.Integer">
            <column name="source_id" />
        </property>
        <property name="price" type="string">
            <column name="price" length="200" />
        </property>
        <property name="descriptionPrice" type="string">
            <column name="description_price" length="300" />
        </property>
        <property name="organisationInformation" type="string">
            <column name="organisation_information" length="2000" />
        </property>
    </class>
</hibernate-mapping>
